tiramisu_cmdline_parser/__init__.py
tiramisu_cmdline_parser/api.py
tiramisu_cmdline_parser-0.6.1.dist-info/LICENSE
tiramisu_cmdline_parser-0.6.1.dist-info/WHEEL
tiramisu_cmdline_parser-0.6.1.dist-info/METADATA
tiramisu_cmdline_parser-0.6.1.dist-info/RECORD
