Metadata-Version: 2.1
Name: tiramisu_cmdline_parser
Version: 0.6.1
Summary: command-line parser using Tiramisu
Author-email: Emmanuel Garette <gnunux@gnunux.info>
Requires-Python: >=3.8
Classifier: License :: OSI Approved :: GNU Library or Lesser General Public License (LGPL)
Classifier: Programming Language :: Python
Classifier: Programming Language :: Python :: 3.8
Classifier: Programming Language :: Python :: 3.9
Classifier: Programming Language :: Python :: 3.10
Classifier: Programming Language :: Python :: 3.11
Classifier: Programming Language :: Python :: 3.12
Classifier: Programming Language :: Python :: 3
Classifier: Operating System :: OS Independent
Classifier: Natural Language :: English
Classifier: Natural Language :: French
Requires-Dist: tiramisu >= 5.0,<6
Project-URL: Home, https://forge.cloud.silique.fr/stove/tiramisu-cmdline-parser
